django_cypress/__init__.py
django_cypress/apps.py
django_cypress/urls.py
django_cypress/views.py
django_cypress/management/__init__.py
django_cypress/management/commands/__init__.py
django_cypress/management/commands/cypress_boilerplate.py
django_cypress/stubs/cypress.config.js
django_cypress/stubs/cypress/e2e/example.cy.js
django_cypress/stubs/cypress/support/commands.js
django_cypress/stubs/cypress/support/index.d.ts
django_cypress/stubs/cypress/support/index.js
tests/__init__.py
tests/test_settings.py
tests/tests.py
tests/urls.py
django_cypress-1.0.1.dist-info/LICENSE
django_cypress-1.0.1.dist-info/METADATA
django_cypress-1.0.1.dist-info/WHEEL
django_cypress-1.0.1.dist-info/top_level.txt
django_cypress-1.0.1.dist-info/RECORD
