Metadata-Version: 2.1
Name: django-cypress
Version: 1.0.1
Summary: Integration of Cypress in a Django project.
Home-page: https://github.com/HelloWorld-PC/django-cypress
Author: HelloWorld PC
License: MIT License
Platform: UNKNOWN
Requires: Django (>=3.2)
